ctef/__init__.py
ctef/ctef.py
ctef/ctef_clustering.py
examples/__init__.py
examples/cell_cycle.py
examples/clustering.py
examples/ellipsoid_gaussian.py
examples/helpers.py
examples/rosenbrock.py
ctef-0.0.4.dist-info/LICENSE.md
ctef-0.0.4.dist-info/METADATA
ctef-0.0.4.dist-info/WHEEL
ctef-0.0.4.dist-info/top_level.txt
ctef-0.0.4.dist-info/RECORD
