Metadata-Version: 2.1
Name: ctef
Version: 0.0.4
Summary: Cayley transform ellipsoid fitting
Home-page: https://github.com/omelikechi/ctef
Author: Omar Melikechi
License: MIT
License-File: LICENSE.md
Requires-Dist: matplotlib
Requires-Dist: numpy
Requires-Dist: scikit-learn
Requires-Dist: scipy
Requires-Dist: tqdm
